pytest_neon/__init__.py
pytest_neon/plugin.py
pytest_neon/py.typed
pytest_neon-2.3.2.dist-info/METADATA
pytest_neon-2.3.2.dist-info/WHEEL
pytest_neon-2.3.2.dist-info/entry_points.txt
pytest_neon-2.3.2.dist-info/licenses/LICENSE
pytest_neon-2.3.2.dist-info/RECORD
