Metadata-Version: 2.4
Name: pytest-neon
Version: 2.3.2
Summary: Pytest plugin for Neon database branch isolation in tests
Project-URL: Homepage, https://github.com/ZainRizvi/pytest-neon
Project-URL: Repository, https://github.com/ZainRizvi/pytest-neon
Project-URL: Issues, https://github.com/ZainRizvi/pytest-neon/issues
Author: Zain Rizvi
License-Expression: MIT
License-File: LICENSE
Keywords: branching,database,neon,postgres,pytest,testing
Classifier: Development Status :: 4 - Beta
Classifier: Framework :: Pytest
Classifier: Intended Audience :: Developers
Classifier: License :: OSI Approved :: MIT License
Classifier: Operating System :: OS Independent
Classifier: Programming Language :: Python :: 3
Classifier: Programming Language :: Python :: 3.9
Classifier: Programming Language :: Python :: 3.10
Classifier: Programming Language :: Python :: 3.11
Classifier: Programming Language :: Python :: 3.12
Classifier: Programming Language :: Python :: 3.13
Classifier: Programming Language :: Python :: 3.14
Classifier: Topic :: Database
Classifier: Topic :: Software Development :: Testing
Requires-Python: >=3.9
Requires-Dist: filelock>=3.0
Requires-Dist: neon-api>=0.1.0
Requires-Dist: pytest>=7.0
Requires-Dist: requests>=2.20
Provides-Extra: dev
Requires-Dist: mypy>=1.0; extra == 'dev'
Requires-Dist: psycopg2-binary>=2.9; extra == 'dev'
Requires-Dist: psycopg[binary]>=3.1; extra == 'dev'
Requires-Dist: pytest-cov>=4.0; extra == 'dev'
Requires-Dist: pytest-mock>=3.0; extra == 'dev'
Requires-Dist: ruff>=0.8; extra == 'dev'
Requires-Dist: sqlalchemy>=2.0; extra == 'dev'
Provides-Extra: psycopg
Requires-Dist: psycopg[binary]>=3.1; extra == 'psycopg'
Provides-Extra: psycopg2
Requires-Dist: psycopg2-binary>=2.9; extra == 'psycopg2'
Provides-Extra: sqlalchemy
Requires-Dist: sqlalchemy>=2.0; extra == 'sqlalchemy'
